bittrade_luno_websocket/__init__.py
bittrade_luno_websocket/channels/__init__.py
bittrade_luno_websocket/channels/orderbook.py
bittrade_luno_websocket/channels/user_stream.py
bittrade_luno_websocket/connection/__init__.py
bittrade_luno_websocket/connection/authenticate.py
bittrade_luno_websocket/connection/generic.py
bittrade_luno_websocket/connection/http.py
bittrade_luno_websocket/connection/public.py
bittrade_luno_websocket/models/__init__.py
bittrade_luno_websocket/models/endpoints.py
bittrade_luno_websocket/models/enhanced_websocket.py
bittrade_luno_websocket/models/orderbook.py
bittrade_luno_websocket/models/request.py
bittrade_luno_websocket/models/response_message.py
bittrade_luno_websocket/models/rest/__init__.py
bittrade_luno_websocket/models/rest/balance.py
bittrade_luno_websocket/models/rest/fee.py
bittrade_luno_websocket/models/rest/get_order.py
bittrade_luno_websocket/models/rest/order.py
bittrade_luno_websocket/models/rest/receive_address.py
bittrade_luno_websocket/models/rest/transfer.py
bittrade_luno_websocket/rest/balance.py
bittrade_luno_websocket/rest/get_book.py
bittrade_luno_websocket/rest/get_fee_info.py
bittrade_luno_websocket/rest/get_order.py
bittrade_luno_websocket/rest/get_receive_address.py
bittrade_luno_websocket/rest/order.py
bittrade_luno_websocket/signing/__init__.py
bittrade_luno_websocket-0.1.8.dist-info/WHEEL
bittrade_luno_websocket-0.1.8.dist-info/METADATA
bittrade_luno_websocket-0.1.8.dist-info/RECORD
