Metadata-Version: 2.1
Name: bittrade-luno-websocket
Version: 0.1.8
Summary: 
Author: Matt
Author-email: matt@techspace.asia
Requires-Python: >=3.11,<4.0
Classifier: Programming Language :: Python :: 3
Classifier: Programming Language :: Python :: 3.11
Requires-Dist: ccxt (>=2.7.91,<3.0.0)
Requires-Dist: elm-framework-helpers (>=0.3.0,<0.4.0)
Requires-Dist: orjson (>=3.8.6,<4.0.0)
Requires-Dist: reactivex (>=4.0.4,<5.0.0)
Requires-Dist: requests (>=2.28.2,<3.0.0)
Requires-Dist: returns (>=0.19.0,<0.20.0)
Requires-Dist: websocket-client (>=1.5.1,<2.0.0)
